undep/__init__.py
undep/cli/main.py
undep/config/loader.py
undep/config/models.py
undep/core/monitor.py
undep/core/updater.py
undep/utils/logger.py
undep-0.1.0.dist-info/LICENSE
undep-0.1.0.dist-info/METADATA
undep-0.1.0.dist-info/WHEEL
undep-0.1.0.dist-info/entry_points.txt
undep-0.1.0.dist-info/RECORD
